ndef/__init__.py
ndef/ndef.py
ndef-0.2.dist-info/LICENSE.txt
ndef-0.2.dist-info/METADATA
ndef-0.2.dist-info/WHEEL
ndef-0.2.dist-info/top_level.txt
ndef-0.2.dist-info/zip-safe
ndef-0.2.dist-info/RECORD
