Metadata-Version: 1.1
Name: ndef
Version: 0.2
Summary: NDEF (NFC Data Exchange Format) parser and verifier
Home-page: http://github.com/kichik/pyndef
Author: Amir Szekely
Author-email: kichik+pyndef@gmail.com
License: zlib/libpng
Platform: UNKNOWN
Classifier: Development Status :: 4 - Beta
Classifier: Intended Audience :: Developers
Classifier: License :: OSI Approved :: zlib/libpng License
Classifier: Programming Language :: Python :: 2.7
Classifier: Programming Language :: Python :: 3.4
Classifier: Programming Language :: Python :: 3.5
Classifier: Programming Language :: Python :: 3.6
Classifier: Programming Language :: Python :: 3.7
Classifier: Programming Language :: Python :: 3.8
